Flask_Triangle3-0.5.3.dist-info/DESCRIPTION.rst
Flask_Triangle3-0.5.3.dist-info/METADATA
Flask_Triangle3-0.5.3.dist-info/RECORD
Flask_Triangle3-0.5.3.dist-info/WHEEL
Flask_Triangle3-0.5.3.dist-info/metadata.json
Flask_Triangle3-0.5.3.dist-info/top_level.txt
flask_triangle/__init__.py
flask_triangle/form.py
flask_triangle/jinja.py
flask_triangle/triangle.py
flask_triangle/helpers/__init__.py
flask_triangle/helpers/html.py
flask_triangle/modifiers/__init__.py
flask_triangle/modifiers/base.py
flask_triangle/modifiers/limits.py
flask_triangle/modifiers/multiple.py
flask_triangle/modifiers/patterns.py
flask_triangle/modifiers/required.py
flask_triangle/modifiers/strict.py
flask_triangle/modifiers/typemod.py
flask_triangle/schema/__init__.py
flask_triangle/schema/base.py
flask_triangle/schema/containers.py
flask_triangle/schema/natural.py
flask_triangle/schema/tools.py
flask_triangle/widgets/__init__.py
flask_triangle/widgets/widget.py
flask_triangle/widgets/standard/__init__.py
flask_triangle/widgets/standard/select.py
flask_triangle/widgets/standard/text.py
