Metadata-Version: 2.0
Name: Flask-Triangle3
Version: 0.5.3
Summary: Integration of AngularJS and Flask.
Home-page: https://github.com/Lightslayer/flask-triangle
Author: Morgan Delahaye-Prat
Author-email: mdp@m-del.fr
License: BSD
Platform: any
Classifier: Development Status :: 4 - Beta
Classifier: Environment :: Web Environment
Classifier: Intended Audience :: Developers
Classifier: License :: OSI Approved :: BSD License
Classifier: Operating System :: OS Independent
Classifier: Programming Language :: Python
Classifier: Topic :: Internet :: WWW/HTTP :: Dynamic Content
Classifier: Topic :: Software Development :: Libraries :: Python Modules
Requires-Dist: flask
Requires-Dist: jsonschema
Requires-Dist: six
